cites_dds/__init__.py
cites_dds/dds.py
cites_dds-1.2.3.dist-info/licenses/LICENSE
cites_dds-1.2.3.dist-info/METADATA
cites_dds-1.2.3.dist-info/WHEEL
cites_dds-1.2.3.dist-info/top_level.txt
cites_dds-1.2.3.dist-info/RECORD
