Metadata-Version: 2.4
Name: cites-dds
Version: 1.2.3
Summary: CITES DDS factory
Author-email: Data Developer <info@sysnet.cz>
Project-URL: Homepage, https://github.com/SYSNET-CZ/cites/tree/master/dds
Classifier: Development Status :: 5 - Production/Stable
Classifier: Programming Language :: Python :: 3
Classifier: Intended Audience :: Developers
Classifier: License :: Free For Home Use
Classifier: Natural Language :: Czech
Classifier: Operating System :: OS Independent
Classifier: Topic :: Software Development :: Libraries
Requires-Python: >=3.9
License-File: LICENSE
Requires-Dist: httpx>=0.28.0
Requires-Dist: sysnet-pyutils>=1.3.3
Requires-Dist: urllib3>=2.3.0
Requires-Dist: types-urllib3>=1.26.25.14
Dynamic: license-file
